{
  "filePath": "/Users/gabriel.franca/repos/docs-vue/docs/src/content/docs/pt-br/pages/menu-principal/release-notes/release-notes.mdx",
  "url": "https://www.azion.com/pt-br/documentacao/documentacao/produtos/release-notes/",
  "suggest": {
    "meta_keywords": "Edge SQL, Azion Marketplace, Azion CLI, Edge Application, Azion Templates, Edge Storage API, Azion Integrations, Digital Certificates, API updates, Edge Computing, Product Releases",
    "meta_description": "Explore the latest updates on Azion's Edge Platform, including Edge SQL, marketplace enhancements, CLI updates, and new integration features.",
    "meta_description_length": 141
  },
  "current": {
    "meta_description": "Veja as últimas mudanças e lançamentos na Plataforma de Edge da Azion, na API Azion, CLI e outros canais e produtos.",
    "meta_keywords": "release notes, Azion Console, api, cli, changelog"
  }
}